ndr_add/__init__.py
ndr_add/add.py
ndr_add-0.1.0.dist-info/METADATA
ndr_add-0.1.0.dist-info/WHEEL
ndr_add-0.1.0.dist-info/top_level.txt
ndr_add-0.1.0.dist-info/RECORD
